{
  "itineraries": [
    {
      "id": "toraja-explorer",
      "name": "Toraja Explorer",
      "duration": "4 Hari 3 Malam",
      "description": "Jelajahi keindahan dan keunikan Tana Toraja dengan mengunjungi situs-situs budaya ikonik dan menikmati keramahan lokal.",
      "image": "https://images.unsplash.com/photo-1518548419970-58e3b4079ab2?w=800",
      "highlights": ["Tongkonan Kete Kesu", "Londa Burial Site", "Lemo Stone Graves", "Batutumonga"],
      "priceRange": "Rp3.500.000 - Rp5.000.000",
      "difficulty": "Mudah",
      "featured": true,
      "days": [
        {
          "day": 1,
          "title": "Makassar - Toraja",
          "activities": ["Perjalanan darat Makassar-Toraja (8 jam)", "Mampir di Bantimurung", "Check-in hotel di Rantepao"]
        },
        {
          "day": 2,
          "title": "Tur Toraja Selatan",
          "activities": ["Kete Kesu", "Londa Burial Cave", "Lemo Stone Graves", "Suaya Royal Cemetery"]
        },
        {
          "day": 3,
          "title": "Tur Toraja Utara",
          "activities": ["Batutumonga sunrise", "Sawah terasering", "Desa tradisional", "Pasar lokal"]
        },
        {
          "day": 4,
          "title": "Kembali ke Makassar",
          "activities": ["Belanja oleh-oleh", "Perjalanan kembali ke Makassar"]
        }
      ]
    },
    {
      "id": "makassar-city-tour",
      "name": "Makassar City Tour",
      "duration": "1 Hari",
      "description": "Eksplorasi kota Makassar dari sisi sejarah, kuliner, dan modernitas dalam satu hari penuh.",
      "image": "https://images.unsplash.com/photo-1552832230-c0197dd311b5?w=800",
      "highlights": ["Fort Rotterdam", "Pantai Losari", "Trans Studio", "Kuliner Lokal"],
      "priceRange": "Rp350.000 - Rp500.000",
      "difficulty": "Mudah",
      "featured": true,
      "days": [
        {
          "day": 1,
          "title": "Full Day Makassar",
          "activities": ["Fort Rotterdam & Museum La Galigo", "Pantai Losari", "Masjid Amirul Mukminin", "Kuliner Coto & Konro", "Sunset di Losari"]
        }
      ]
    },
    {
      "id": "bira-beach-escape",
      "name": "Bira Beach Escape",
      "duration": "3 Hari 2 Malam",
      "description": "Liburan pantai sempurna di Bira dengan snorkeling, diving, dan menikmati seafood segar.",
      "image": "https://images.unsplash.com/photo-1506929562872-bb421503ef21?w=800",
      "highlights": ["Pantai Bira", "Galangan Pinisi", "Snorkeling", "Sunset"],
      "priceRange": "Rp2.000.000 - Rp3.500.000",
      "difficulty": "Mudah",
      "featured": true,
      "days": [
        {
          "day": 1,
          "title": "Makassar - Bira",
          "activities": ["Perjalanan ke Bira (5 jam)", "Visit galangan Pinisi Bulukumba", "Check-in resort", "Sunset di pantai"]
        },
        {
          "day": 2,
          "title": "Eksplorasi Bira",
          "activities": ["Snorkeling trip ke Pulau Liukang", "Berenang di pantai", "Seafood dinner"]
        },
        {
          "day": 3,
          "title": "Kembali ke Makassar",
          "activities": ["Sunrise view", "Belanja oleh-oleh", "Perjalanan kembali"]
        }
      ]
    },
    {
      "id": "karst-adventure",
      "name": "Karst Adventure Maros",
      "duration": "1 Hari",
      "description": "Petualangan di kawasan karst Maros-Pangkep dengan trekking, susur sungai, dan eksplorasi gua.",
      "image": "https://images.unsplash.com/photo-1464822759023-fed622ff2c3b?w=800",
      "highlights": ["Rammang-Rammang", "Bantimurung", "Gua Prasejarah", "Sungai Pute"],
      "priceRange": "Rp400.000 - Rp700.000",
      "difficulty": "Sedang",
      "featured": false,
      "days": [
        {
          "day": 1,
          "title": "Maros Karst Exploration",
          "activities": ["Bantimurung Waterfall", "Susur sungai Rammang-Rammang", "Trekking di karst", "Gua Pattunuang"]
        }
      ]
    }
  ]
}
